cellseg_models_pytorch/__init__.py
cellseg_models_pytorch/datasets/__init__.py
cellseg_models_pytorch/datasets/pannuke.py
cellseg_models_pytorch/datasets/tests/__init__.py
cellseg_models_pytorch/decoders/__init__.py
cellseg_models_pytorch/decoders/long_skips/__init__.py
cellseg_models_pytorch/decoders/long_skips/cross_attn_skip.py
cellseg_models_pytorch/decoders/long_skips/longskip_module.py
cellseg_models_pytorch/decoders/long_skips/merging/__init__.py
cellseg_models_pytorch/decoders/long_skips/merging/cat.py
cellseg_models_pytorch/decoders/long_skips/merging/merge_block.py
cellseg_models_pytorch/decoders/long_skips/merging/sum.py
cellseg_models_pytorch/decoders/long_skips/stem_skip.py
cellseg_models_pytorch/decoders/long_skips/unet.py
cellseg_models_pytorch/decoders/long_skips/unet3p.py
cellseg_models_pytorch/decoders/long_skips/unetpp.py
cellseg_models_pytorch/decoders/multitask_decoder.py
cellseg_models_pytorch/decoders/tests/__init__.py
cellseg_models_pytorch/decoders/tests/test_decoders.py
cellseg_models_pytorch/decoders/tests/test_merge.py
cellseg_models_pytorch/decoders/unet_decoder.py
cellseg_models_pytorch/decoders/unet_decoder_stage.py
cellseg_models_pytorch/encoders/__init__.py
cellseg_models_pytorch/encoders/encoder.py
cellseg_models_pytorch/encoders/encoder_upsampler.py
cellseg_models_pytorch/encoders/timm_encoder.py
cellseg_models_pytorch/inference/__init__.py
cellseg_models_pytorch/inference/post_processor.py
cellseg_models_pytorch/inference/predictor.py
cellseg_models_pytorch/inference/tests/__init__.py
cellseg_models_pytorch/inference/tests/data/test1.png
cellseg_models_pytorch/inference/tests/data/test2.png
cellseg_models_pytorch/inference/tests/test_inference.py
cellseg_models_pytorch/inference/wsi_segmenter.py
cellseg_models_pytorch/losses/__init__.py
cellseg_models_pytorch/losses/criterions/__init__.py
cellseg_models_pytorch/losses/criterions/bce.py
cellseg_models_pytorch/losses/criterions/ce.py
cellseg_models_pytorch/losses/criterions/dice.py
cellseg_models_pytorch-0.1.30.dist-info/METADATA
cellseg_models_pytorch-0.1.30.dist-info/WHEEL
cellseg_models_pytorch-0.1.30.dist-info/licenses/LICENSE
cellseg_models_pytorch-0.1.30.dist-info/RECORD
