Metadata-Version: 2.4
Name: cellseg_models_pytorch
Version: 0.1.30
Summary: Python library for 2D cell/nuclei instance segmentation models written with PyTorch.
License: MIT
License-File: LICENSE
Keywords: cell segmentation,nuclei segmentation,pytorch,pytorch-lightning
Author: Okunator
Author-email: oskari.lehtonen@helsinki.fi
Requires-Python: >=3.10,<4.0
Classifier: License :: OSI Approved :: MIT License
Classifier: Programming Language :: Python :: 3
Classifier: Programming Language :: Python :: 3.10
Classifier: Programming Language :: Python :: 3.11
Classifier: Programming Language :: Python :: 3.12
Classifier: Programming Language :: Python :: 3.13
Classifier: Programming Language :: Python :: 3.14
Requires-Dist: geopandas (>=1.0.1,<2.0.0)
Requires-Dist: libpysal (>=4.12.1,<5.0.0)
Requires-Dist: mpire[dill] (>=2.10.2,<3.0.0)
Requires-Dist: numba (>=0.60.0,<0.61.0)
Requires-Dist: numpy (>=1.24,<2.0)
Requires-Dist: opencv-python (>=4.8,<5.0)
Requires-Dist: pyarrow (>=16.1.0,<17.0.0)
Requires-Dist: rasterio (>=1.4.3,<2.0.0)
Requires-Dist: requests (>=2.28.0,<3.0.0)
Requires-Dist: scikit-image (>=0.25,<0.26)
Requires-Dist: scikit-learn (>=1.3.0,<2.0.0)
Requires-Dist: scipy (>=1.14,<2.0)
Requires-Dist: timm (>=1.0.7,<2.0.0)
Requires-Dist: torch (>=2.0.0,<3.0.0)
Requires-Dist: tqdm (>=4.64.0,<5.0.0)
Project-URL: Homepage, https://github.com/okunator/cellseg_models.pytorch
Project-URL: Repository, https://github.com/okunator/cellseg_models.pytorch
